[
    {
        "label": "UX design",
        "title": "UX &amp; Web design master course A-Z",
        "author": "Sheikh Al",
        "progress": 48
    },
    {
        "label": "Animation",
        "title": "Adobe after effects masterclass",
        "author": "Surja Sen",
        "progress": 78
    },
    {
        "label": "Illustration",
        "title": "How to shape your concept",
        "author": "Wahab",
        "progress": 81
    },
    {
        "label": "Adobe Illustrator",
        "title": "Adobe Illustrator Master Class A-Z",
        "author": "Mansurul",
        "progress": 88
    }
]